KdnTools/__init__.py
KdnTools/Tools/DataFetcher.py
KdnTools/Tools/DbManage.py
KdnTools/Tools/DriveLetter.py
KdnTools/Tools/EmailValidator.py
KdnTools/Tools/Generation.py
KdnTools/Tools/Lists.py
KdnTools/Tools/RandNumber.py
KdnTools/Tools/String.py
KdnTools/Tools/User.py
KdnTools/Tools/WordCount.py
KdnTools/Tools/__init__.py
KdnTools-1.9.1.dist-info/METADATA
KdnTools-1.9.1.dist-info/WHEEL
KdnTools-1.9.1.dist-info/top_level.txt
KdnTools-1.9.1.dist-info/RECORD
