Metadata-Version: 2.1
Name: KdnTools
Version: 1.9.1
Summary: Useful tools for every project.
Home-page: https://github.com/KdntNinja/Code/tree/main/Python/KdnTools
Author: KdntNinja
Project-URL: Source, https://github.com/KdntNinja/Code/tree/main/Python/KdnTools
Classifier: Development Status :: 5 - Production/Stable
Classifier: Intended Audience :: Developers
Classifier: Programming Language :: Python :: 3.10
Classifier: Programming Language :: Python :: 3.11
Classifier: Programming Language :: Python :: 3.12
Classifier: Operating System :: OS Independent
Requires-Python: >=3.10,<3.13
Requires-Dist: colorama >=0.4.6
Requires-Dist: prettytable >=3.9.0
Requires-Dist: matplotlib >=3.8.1
Requires-Dist: numpy >=1.26.2
Requires-Dist: requests >=2.31.0
Requires-Dist: Flask >=2.3.2
Requires-Dist: KdnTools >=1.8.1
Requires-Dist: setuptools >=68.2.2
Requires-Dist: ping3 >=4.0.4
Requires-Dist: aiodns >=3.1.1
Requires-Dist: werkzeug >=3.0.0
